MANIFEST.in
README.md
requirements.txt
setup.cfg
setup.py
SciDataTool/__init__.py
SciDataTool.egg-info/PKG-INFO
SciDataTool.egg-info/SOURCES.txt
SciDataTool.egg-info/dependency_links.txt
SciDataTool.egg-info/requires.txt
SciDataTool.egg-info/top_level.txt
SciDataTool/Classes/Data.py
SciDataTool/Classes/Data1D.py
SciDataTool/Classes/DataDual.py
SciDataTool/Classes/DataFreq.py
SciDataTool/Classes/DataLinspace.py
SciDataTool/Classes/DataND.py
SciDataTool/Classes/DataPattern.py
SciDataTool/Classes/DataTime.py
SciDataTool/Classes/Norm_affine.py
SciDataTool/Classes/Norm_func.py
SciDataTool/Classes/Norm_indices.py
SciDataTool/Classes/Norm_ref.py
SciDataTool/Classes/Norm_vector.py
SciDataTool/Classes/Normalization.py
SciDataTool/Classes/RequestedAxis.py
SciDataTool/Classes/VectorField.py
SciDataTool/Classes/__init__.py
SciDataTool/Classes/_check.py
SciDataTool/Classes/_frozen.py
SciDataTool/Classes/import_all.py
SciDataTool/Data/__init__.py
SciDataTool/Functions/__init__.py
SciDataTool/Functions/change_referential.py
SciDataTool/Functions/conversions.py
SciDataTool/Functions/copy.py
SciDataTool/Functions/derivation_integration.py
SciDataTool/Functions/fft_functions.py
SciDataTool/Functions/filter_spectral_leakage.py
SciDataTool/Functions/fix_axes_order.py
SciDataTool/Functions/interpolations.py
SciDataTool/Functions/is_axes_in_order.py
SciDataTool/Functions/load.py
SciDataTool/Functions/load_switch.py
SciDataTool/Functions/nudft_functions.py
SciDataTool/Functions/omp.py
SciDataTool/Functions/parser.py
SciDataTool/Functions/save.py
SciDataTool/Functions/set_routines.py
SciDataTool/Functions/sum_convolution.py
SciDataTool/Functions/sum_mean.py
SciDataTool/Functions/symmetries.py
SciDataTool/Functions/Load/__init__.py
SciDataTool/Functions/Load/import_class.py
SciDataTool/Functions/Load/load_hdf5.py
SciDataTool/Functions/Load/load_json.py
SciDataTool/Functions/Load/load_pkl.py
SciDataTool/Functions/Plot/__init__.py
SciDataTool/Functions/Plot/init_fig.py
SciDataTool/Functions/Plot/plot_2D.py
SciDataTool/Functions/Plot/plot_3D.py
SciDataTool/Functions/Plot/plot_4D.py
SciDataTool/Methods/__init__.py
SciDataTool/Methods/Data/__init__.py
