Metadata-Version: 2.1
Name: SciDataTool
Version: 2.5.0
Summary: Scientific Data Tool
Home-page: https://github.com/Eomys/SciDataTool
Author: Helene Toubin
Author-email: helene.toubin@eomys.com
License: UNKNOWN
Download-URL: https://github.com/Eomys/SciDataTool/archive/2.5.0.tar.gz
Platform: UNKNOWN
Classifier: Programming Language :: Python :: 3
Classifier: License :: OSI Approved :: Apache Software License
Classifier: Operating System :: OS Independent
Requires-Python: >=3.8
